quantstats/__init__.py
quantstats/api.py
quantstats/stats.py
jqrquantstats-0.0.5.dist-info/METADATA
jqrquantstats-0.0.5.dist-info/WHEEL
jqrquantstats-0.0.5.dist-info/licenses/LICENSE.txt
jqrquantstats-0.0.5.dist-info/RECORD
