Metadata-Version: 2.4
Name: jqrquantstats
Version: 0.0.5
Summary: Toying with quantstats
Project-URL: repository, https://github.com/tschm/quantstats
Author-email: tschm <thomas.schmelzer@gmail.com>
License-File: LICENSE.txt
Requires-Python: >=3.10
Requires-Dist: kaleido==0.2.1
Requires-Dist: numpy>=2.2.3
Requires-Dist: pandas>=2.2.3
Requires-Dist: plotly>=6.0.0
Requires-Dist: scipy>=1.15.0
Provides-Extra: dev
Requires-Dist: pre-commit==4.2.0; extra == 'dev'
Requires-Dist: pytest-cov==6.1.1; extra == 'dev'
Requires-Dist: pytest==8.3.5; extra == 'dev'
Requires-Dist: yfinance==0.2.56; extra == 'dev'
